{
  "proveedores": [
    {
      "id": "421526a5-74fb-44b3-9b27-3b3203383229",
      "nombre_servicio": "Mariachis Locos",
      "imagen": "https://ui-avatars.com/api/mariachis",
      "experiencia": "10 años",
      "servicio": "Servicio de Música de Mariachis",
      "descripcion": "Tocando música regional y ranchera desde hace 10 años. Mariachis locos ofrece sus servicios para todo tipo de eventos, ánimo!",
      "categoria": "Música",
      "ubicación": "Ciudad de México",
      "rango_precio_mxn": [300, 1000],
      "telefono": "+525523438888",
      "modalidad": "En establecimiento",
      "servicios": ["Servicio de Música de Mariachis",
      "Serenatas",
      "Música para fiestas"],
      "todo_score": 4
    },
    {
      "id": "f0ee49dc-6b01-4164-b810-427ae036354e",
      "nombre_servicio": "Clínica Dental Sonrisa Viva",
      "imagen": "https://ui-avatars.com/api/dentista",
      "experiencia": "8 años",
      "servicio": "Odontología general",
      "descripcion": "Atención dental profesional con tecnología moderna y atención personalizada.",
      "categoria": "Salud",
      "ubicación": "Guadalajara, Jalisco",
      "rango_precio_mxn":  [400, 2000],
      "telefono": "+523316554321",
      "modalidad": "En establecimiento",
      "servicios": ["Limpieza dental",
      "Blanqueamiento",
      "Ortodoncia"],
      "todo_score": 5
    },
    {
      "id": "b205026e-a434-496e-abd5-291779b64849",
      "nombre_servicio": "Corte & Estilo Studio",
      "imagen": "https://ui-avatars.com/api/estilista",
      "experiencia": "12 años",
      "servicio": "Estilismo y peluquería",
      "descripcion": "Salón especializado en cortes modernos y colorimetría profesional.",
      "categoria": "Belleza",
      "ubicación": "Monterrey, Nuevo León",
      "rango_precio_mxn":  [250, 1500],
      "telefono": "+528182344556",
      "modalidad": "En establecimiento",
      "servicios": ["Corte de cabello",
      "Tinte y color",
      "Peinados para eventos"],
      "todo_score": 5
    },
    {
      "id": "04fc0920-1b3f-450c-8b2c-feb786bf97c4",
      "nombre_servicio": "Taller de Cerámica Tierra Viva",
      "imagen": "https://ui-avatars.com/api/ceramica",
      "experiencia": "6 años",
      "servicio": "Artesanía en cerámica personalizada",
      "descripcion": "Creación de piezas únicas hechas a mano con diseños personalizados.",
      "categoria": "Artesanías",
      "ubicación": "Oaxaca, Oaxaca",
      "rango_precio_mxn": [200, 3000],
      "telefono": "+529511223344",
      "modalidad": "A domicilio",
      "servicios": ["Talleres de cerámica",
      "Piezas personalizadas",
      "Restauración de cerámica"],
      "todo_score": 4
    },
    {
      "id": "3f5f4951-a40c-4151-b762-4d488d809020",
      "nombre_servicio": "Fotografía Lentes de Oro",
      "imagen": "https://ui-avatars.com/api/fotografo",
      "experiencia": "9 años",
      "servicio": "Fotografía profesional",
      "descripcion": "Fotografía para eventos, retratos y sesiones artísticas con atención al detalle.",
      "categoria": "Fotografía",
      "ubicación": "Puebla, Puebla",
      "rango_precio_mxn": [800, 5000],
      "telefono": "+522221234567",
      "modalidad": "A domicilio",
      "servicios": ["Fotografía de eventos",
      "Retratos",
      "Edición profesional"],
      "todo_score": 5
    },
    {
      "id": "05019145-9714-4c49-9a7d-34b0847ff2df",
      "nombre_servicio": "Masajes Relajarte",
      "imagen": "https://ui-avatars.com/api/masajista",
      "experiencia": "7 años",
      "servicio": "Terapia de masaje",
      "descripcion": "Masajes terapéuticos y de relajación para eliminar tensiones.",
      "categoria": "Salud y Bienestar",
      "ubicación": "Querétaro, Querétaro",
      "rango_precio_mxn": [400, 1200],
      "telefono": "+524422113344",
      "modalidad": "A domicilio",
      "servicios": ["Masaje relajante",
      "Masaje deportivo",
      "Masaje con piedras calientes"],
      "todo_score": 4
    },
    {
      "id": "67147f87-1b53-445c-8589-55bb9563f521",
      "nombre_servicio": "Tatuajes Línea Fina",
      "imagen": "https://ui-avatars.com/api/tatuador",
      "experiencia": "5 años",
      "servicio": "Tatuajes personalizados",
      "descripcion": "Diseños personalizados con técnicas seguras y materiales de alta calidad.",
      "categoria": "Arte corporal",
      "ubicación": "Tijuana, Baja California",
      "rango_precio_mxn": [800, 4000],
      "telefono": "+526641122333",
      "modalidad": "En establecimiento",
      "servicios": ["Tatuajes en línea fina",
      "Diseños personalizados",
      "Cubrimiento de tatuajes"],
      "todo_score": 5
    },
    {
      "id": "40f5784d-798a-42ca-9e4a-52061848587d",
      "nombre_servicio": "Clases de Piano Melodía",
      "imagen": "https://ui-avatars.com/api/piano",
      "experiencia": "10 años",
      "servicio": "Clases de piano particulares",
      "descripcion": "Clases personalizadas para todas las edades, en casa o en línea.",
      "categoria": "Educación musical",
      "ubicación": "Ciudad de México",
      "rango_precio_mxn": [300, 800],
      "telefono": "+525522334455",
      "modalidad": "A domicilio",
      "servicios": ["Clases individuales",
      "Preparación para exámenes",
      "Lectura musical"],
      "todo_score": 4
    },
    {
      "id": "a93d53e9-a98e-4c56-9bbc-85b829a6e4d3",
      "nombre_servicio": "Reparaciones Eléctricas García",
      "imagen": "https://ui-avatars.com/api/electricista",
      "experiencia": "15 años",
      "servicio": "Servicios eléctricos residenciales",
      "descripcion": "Instalaciones, mantenimiento y reparaciones eléctricas con garantía.",
      "categoria": "Servicios técnicos",
      "ubicación": "Toluca, Estado de México",
      "rango_precio_mxn": [500, 2500],
      "telefono": "+527221234111",
      "modalidad": "A domicilio",
      "servicios": ["Instalación de cableado",
      "Revisión de cortos",
      "Mantenimiento preventivo"],
      "todo_score": 5
    },
    {
      "id": "c8a86fca-ccd9-4781-9aef-284945756898",
      "nombre_servicio": "Pasteles Dulce Encanto",
      "imagen": "https://ui-avatars.com/api/pastelera",
      "experiencia": "9 años",
      "servicio": "Repostería artesanal",
      "descripcion": "Pasteles personalizados y postres para eventos con ingredientes frescos.",
      "categoria": "Alimentos",
      "ubicación": "León, Guanajuato",
      "rango_precio_mxn": [300, 2500],
      "telefono": "+524771112233",
      "modalidad": "A domicilio",
      "servicios": ["Pasteles de boda",
      "Cupcakes personalizados",
      "Postres temáticos"],
      "todo_score": 5
    },
    {
      "id": "0f12e0d9-b610-4256-b17e-db99c2fe794f",
      "nombre_servicio": "Mecánica Express López",
      "imagen": "https://ui-avatars.com/api/mecanico",
      "experiencia": "20 años",
      "servicio": "Reparación automotriz",
      "descripcion": "Mecánico profesional con experiencia en mantenimiento de autos nacionales y extranjeros.",
      "categoria": "Automotriz",
      "ubicación": "Zapopan, Jalisco",
      "rango_precio_mxn": [500, 3000],
      "telefono": "+523316667788",
      "modalidad": "A domicilio",
      "servicios": ["Cambio de aceite",
      "Revisión de motor",
      "Frenos y suspensión"],
      "todo_score": 4
    },
    {
      "id": "f9da5f4d-7943-4bf3-93ea-6c11a2bf5a4e",
      "nombre_servicio": "Consultorio Médico Salud Total",
      "imagen": "https://ui-avatars.com/api/doctor",
      "experiencia": "11 años",
      "servicio": "Atención médica general",
      "descripcion": "Consultas médicas y seguimiento personalizado para pacientes.",
      "categoria": "Salud",
      "ubicación": "Mérida, Yucatán",
      "rango_precio_mxn": [400, 1200],
      "telefono": "+529991112222",
      "modalidad": "En establecimiento",
      "servicios": ["Consulta general",
      "Certificados médicos",
      "Control de enfermedades crónicas"],
      "todo_score": 5
    },
    {
      "id": "9a8cc225-c79d-45c6-82b0-6b0e44cc3549",
      "nombre_servicio": "Sastrería El Corte Fino",
      "imagen": "https://ui-avatars.com/api/sastre",
      "experiencia": "25 años",
      "servicio": "Sastrería a medida",
      "descripcion": "Trajes personalizados con materiales de alta calidad y ajuste perfecto.",
      "categoria": "Moda",
      "ubicación": "Ciudad de México",
      "rango_precio_mxn": [1500, 8000],
      "telefono": "+525558992211",
      "modalidad": "En establecimiento",
      "servicios": ["Trajes a medida",
      "Arreglos de ropa",
      "Diseño personalizado"],
      "todo_score": 5
    },
    {
      "id": "a1c4b4bd-531e-4eac-ba7b-beca9be7faf8",
      "nombre_servicio": "Clases de Yoga Vital",
      "imagen": "https://ui-avatars.com/api/yoga",
      "experiencia": "6 años",
      "servicio": "Instrucción de yoga",
      "descripcion": "Clases presenciales y en línea enfocadas en el bienestar físico y mental.",
      "categoria": "Bienestar",
      "ubicación": "Cancún, Quintana Roo",
      "rango_precio_mxn": [200, 700],
      "telefono": "+529982113322",
      "modalidad": "A domicilio",
      "servicios": ["Yoga individual",
      "Yoga en grupo",
      "Meditación guiada"],
      "todo_score": 4
    },
    {
      "id": "762e743e-f8fe-4042-a9dd-530a169d5363",
      "nombre_servicio": "Carpintería Los Robles",
      "imagen": "https://ui-avatars.com/api/carpintero",
      "experiencia": "18 años",
      "servicio": "Muebles personalizados en madera",
      "descripcion": "Diseño y fabricación de muebles a medida con maderas locales.",
      "categoria": "Artesanías",
      "ubicación": "San Luis Potosí, SLP",
      "rango_precio_mxn": [1500, 10000],
      "telefono": "+524441556677",
      "modalidad": "A domicilio",
      "servicios": ["Muebles personalizados",
      "Restauración de muebles",
      "Instalación de closets"],
      "todo_score": 5
    },
    {
      "id": "f09fad7d-abdc-4ae3-a697-401050137135",
      "nombre_servicio": "Clases de Guitarra Ritmo & Cuerda",
      "imagen": "https://ui-avatars.com/api/guitarra",
      "experiencia": "9 años",
      "servicio": "Clases de guitarra",
      "descripcion": "Aprendizaje práctico de guitarra acústica y eléctrica.",
      "categoria": "Música",
      "ubicación": "Morelia, Michoacán",
      "rango_precio_mxn": [250, 800],
      "telefono": "+524433223344",
      "modalidad": "A domicilio",
      "servicios": ["Clases individuales",
      "Técnicas de improvisación",
      "Lectura musical"],
      "todo_score": 4
    },
    {
      "id": "e9f0a12d-d171-4a12-bbc6-d8567af8f26f",
      "nombre_servicio": "Fotografía de Producto StudioFlash",
      "imagen": "https://ui-avatars.com/api/fotoproducto",
      "experiencia": "5 años",
      "servicio": "Fotografía comercial",
      "descripcion": "Fotografía profesional para catálogos y redes sociales.",
      "categoria": "Fotografía",
      "ubicación": "Monterrey, Nuevo León",
      "rango_precio_mxn": [700, 3000],
      "telefono": "+528180003333",
      "modalidad": "En establecimiento",
      "servicios": ["Fotografía de producto",
      "Edición y retoque",
      "Sesiones para ecommerce"],
      "todo_score": 5
    },
    {
      "id": "8cc3bba6-94ca-4418-86ca-55d2b9592428",
      "nombre_servicio": "Floristería Rosas del Alba",
      "imagen": "https://ui-avatars.com/api/florista",
      "experiencia": "14 años",
      "servicio": "Diseño floral para eventos",
      "descripcion": "Arreglos florales personalizados para bodas, cumpleaños y eventos empresariales.",
      "categoria": "Eventos",
      "ubicación": "Hermosillo, Sonora",
      "rango_precio_mxn": [300, 5000],
      "telefono": "+526622114455",
      "modalidad": "A domicilio",
      "servicios": ["Ramos personalizados",
      "Decoración de eventos",
      "Entrega a domicilio"],
      "todo_score": 4
    },
    {
      "id": "e78a6583-d77a-412f-99dd-4c56f7903b21",
      "nombre_servicio": "Entrenador Personal FitMove",
      "imagen": "https://ui-avatars.com/api/entrenador",
      "experiencia": "7 años",
      "servicio": "Entrenamiento físico personalizado",
      "descripcion": "Entrenamientos personalizados enfocados en fuerza y resistencia.",
      "categoria": "Deporte",
      "ubicación": "Guadalajara, Jalisco",
      "rango_precio_mxn": [300, 1000],
      "telefono": "+523312227744",
      "modalidad": "A domicilio",
      "servicios": ["Entrenamiento funcional",
      "Plan de nutrición",
      "Asesoría deportiva"],
      "todo_score": 5
    },
    {
      "id": "e599e2a4-bbc4-40cd-a5a0-039a0c9921e0",
      "nombre_servicio": "Terapia Psicológica Balance",
      "imagen": "https://ui-avatars.com/api/psicologa",
      "experiencia": "10 años",
      "servicio": "Atención psicológica",
      "descripcion": "Sesiones individuales y de pareja enfocadas en el bienestar emocional.",
      "categoria": "Salud mental",
      "ubicación": "Ciudad de México",
      "rango_precio_mxn": [500, 1200],
      "telefono": "+525521113355",
      "modalidad": "En establecimiento",
      "servicios": ["Terapia individual",
      "Terapia de pareja",
      "Orientación emocional"],
      "todo_score": 5
    },
    {
      "id": "a6492c07-f2d7-49c5-b307-6774534fd9a6",
      "nombre_servicio": "Clases de Costura CreaTextil",
      "imagen": "https://ui-avatars.com/api/costurera",
      "experiencia": "13 años",
      "servicio": "Clases y confección textil",
      "descripcion": "Aprende a confeccionar ropa o solicita prendas personalizadas.",
      "categoria": "Educación y Moda",
      "ubicación": "Chihuahua, Chihuahua",
      "rango_precio_mxn": [250, 1500],
      "telefono": "+526141234567",
      "modalidad": "A domicilio",
      "servicios": ["Clases de costura",
      "Diseño de prendas",
      "Arreglos personalizados"],
      "todo_score": 4
    }
  ]
}
